detl/__init__.py
detl/core.py
detl/parsing/__init__.py
detl/parsing/common.py
detl/parsing/dw4.py
detl/parsing/dw5.py
detl/parsing/utils.py
detl-1.1.3.dist-info/LICENSE.md
detl-1.1.3.dist-info/METADATA
detl-1.1.3.dist-info/WHEEL
detl-1.1.3.dist-info/top_level.txt
detl-1.1.3.dist-info/RECORD
