Metadata-Version: 2.1
Name: detl
Version: 1.1.3
Summary: Package for parsing and transforming DASware raw data exports.
Home-page: https://github.com/JuBiotech/detl
Author: IBG-1
License: GNU Affero General Public License v3.0
Platform: UNKNOWN
Classifier: Programming Language :: Python
Classifier: Operating System :: OS Independent
Classifier: Programming Language :: Python :: 3.8
Classifier: Intended Audience :: Science/Research
Classifier: License :: OSI Approved :: GNU Affero General Public License v3
License-File: LICENSE.md
Requires-Dist: numpy
Requires-Dist: pandas
